pylandtemp/__init__.py
pylandtemp/exceptions.py
pylandtemp/pylandtemp.py
pylandtemp/runner.py
pylandtemp/utils.py
pylandtemp/emissivity/__init__.py
pylandtemp/emissivity/algorithms.py
pylandtemp/emissivity/emissivity.py
pylandtemp/temperature/__init__.py
pylandtemp/temperature/brightness_temperature.py
pylandtemp/temperature/temperature.py
pylandtemp/temperature/utils.py
pylandtemp/temperature/algorithms/__init__.py
pylandtemp/temperature/algorithms/mono_window.py
pylandtemp/temperature/algorithms/split_window/__init__.py
pylandtemp/temperature/algorithms/split_window/algorithms.py
pylandtemp-0.0.1a1.dist-info/LICENSE
pylandtemp-0.0.1a1.dist-info/METADATA
pylandtemp-0.0.1a1.dist-info/WHEEL
pylandtemp-0.0.1a1.dist-info/top_level.txt
pylandtemp-0.0.1a1.dist-info/RECORD
