Metadata-Version: 2.1
Name: pylandtemp
Version: 0.0.1a1
Summary: Compute land surface temperature(LST) from Landsat-8 data
Home-page: https://github.com/pylandtemp/pylandtemp
Author: Oladimeji Mudele
License: Apache
Keywords: Image processing,Landsat,Satellite images
Platform: UNKNOWN
Classifier: Development Status :: 3 - Alpha
Classifier: Intended Audience :: Education
Classifier: Topic :: Software Development :: Build Tools
Classifier: Programming Language :: Python :: 3.8
Requires-Python: >=3.8
License-File: LICENSE
Requires-Dist: numpy
